gokulang/__init__.py
gokulang/gokulang.py
gokulang/romakana.py
gokulang/test_gokulang.py
gokulang-1.0.2.dist-info/METADATA
gokulang-1.0.2.dist-info/WHEEL
gokulang-1.0.2.dist-info/top_level.txt
gokulang-1.0.2.dist-info/RECORD
