Metadata-Version: 2.1
Name: gokulang
Version: 1.0.2
Summary: To translate Japanese sentences into Son Goku accent.
Home-page: https://github.com/shonansurvivors/goku-lang
Author: shonansurvivors
Author-email: shonansurvivors@gmail.com
License: MIT
Keywords: gokulang,goku-lang
Platform: UNKNOWN
Classifier: License :: OSI Approved :: MIT License
Classifier: Programming Language :: Python :: 3.6
Requires-Dist: janome
Requires-Dist: pykakasi
Requires-Dist: semidbm
Requires-Dist: six
